LICENSE
MANIFEST.in
README.md
README.rst
setup.py
django_liar.egg-info/PKG-INFO
django_liar.egg-info/SOURCES.txt
django_liar.egg-info/dependency_links.txt
django_liar.egg-info/top_level.txt
liar/__init__.py
liar/models.py
liar/utils.py
testapp/manage.py