Metadata-Version: 1.1
Name: django-liar
Version: 0.1.1
Summary: A simple django app that invalidates url resolving of apps.
Home-page: https://github.com/lalo73/django-liar
Author: Leandro Gomez
Author-email: leandro.gz73@gmail.com
License: BSD License
Platform: UNKNOWN
Classifier: Environment :: Web Environment
Classifier: Framework :: Django
Classifier: Intended Audience :: Developers
Classifier: License :: OSI Approved :: BSD License
Classifier: Operating System :: OS Independent
Classifier: Programming Language :: Python
Classifier: Programming Language :: Python :: 2.6
Classifier: Programming Language :: Python :: 2.7
Classifier: Topic :: Internet :: WWW/HTTP
Classifier: Topic :: Internet :: WWW/HTTP :: Dynamic Content
